setup.py
train_duy_custom/__init__.py
train_duy_custom/process_data.py
train_duy_custom/train.py
train_duy_custom/train_model.py
train_duy_custom/train_model_argparam.py
train_duy_custom/utils.py
train_duy_custom.egg-info/PKG-INFO
train_duy_custom.egg-info/SOURCES.txt
train_duy_custom.egg-info/dependency_links.txt
train_duy_custom.egg-info/top_level.txt